grassmann_tensor/__init__.py
grassmann_tensor/_version.py
grassmann_tensor/tensor.py
grassmann_tensor/version.py
grassmann_tensor-0.0.1a20.dist-info/licenses/LICENSE.md
grassmann_tensor-0.0.1a20.dist-info/METADATA
grassmann_tensor-0.0.1a20.dist-info/WHEEL
grassmann_tensor-0.0.1a20.dist-info/top_level.txt
grassmann_tensor-0.0.1a20.dist-info/RECORD
