Metadata-Version: 2.4
Name: grassmann-tensor
Version: 0.0.1a20
Summary: A Grassmann algebra tensor package
Author-email: Hao Zhang <hzhangxyz@outlook.com>
License-Expression: GPL-3.0-or-later
Requires-Python: >=3.10
License-File: LICENSE.md
Requires-Dist: torch
Provides-Extra: dev
Requires-Dist: mypy; extra == "dev"
Requires-Dist: pytest; extra == "dev"
Requires-Dist: pytest-cov; extra == "dev"
Requires-Dist: ruff; extra == "dev"
Dynamic: license-file
